MANIFEST.in
README.txt
setup.cfg
setup.py
medialog/.DS_Store
medialog/__init__.py
medialog.mascutheme.egg-info/PKG-INFO
medialog.mascutheme.egg-info/SOURCES.txt
medialog.mascutheme.egg-info/dependency_links.txt
medialog.mascutheme.egg-info/entry_points.txt
medialog.mascutheme.egg-info/namespace_packages.txt
medialog.mascutheme.egg-info/not-zip-safe
medialog.mascutheme.egg-info/paster_plugins.txt
medialog.mascutheme.egg-info/requires.txt
medialog.mascutheme.egg-info/top_level.txt
medialog/mascutheme/.DS_Store
medialog/mascutheme/__init__.py
medialog/mascutheme/configure.zcml
medialog/mascutheme/profiles.zcml
medialog/mascutheme/setuphandlers.py
medialog/mascutheme/skins.zcml
medialog/mascutheme/tests.py
medialog/mascutheme/version.txt
medialog/mascutheme/browser/.DS_Store
medialog/mascutheme/browser/__init__.py
medialog/mascutheme/browser/configure.zcml
medialog/mascutheme/browser/interfaces.py
medialog/mascutheme/browser/managetopportlets.pt
medialog/mascutheme/browser/mascutheme_colophon.pt
medialog/mascutheme/browser/mascutheme_siteactions.pt
medialog/mascutheme/browser/topportlets.pt
medialog/mascutheme/browser/views.py
medialog/mascutheme/browser/images/README.txt
medialog/mascutheme/browser/stylesheets/main.css
medialog/mascutheme/locales/README.txt
medialog/mascutheme/profiles/.DS_Store
medialog/mascutheme/profiles/default/actions.xml
medialog/mascutheme/profiles/default/cssregistry.xml
medialog/mascutheme/profiles/default/jsregistry.xml
medialog/mascutheme/profiles/default/medialog.mascutheme_various.txt
medialog/mascutheme/profiles/default/metadata.xml
medialog/mascutheme/profiles/default/portlets.xml
medialog/mascutheme/profiles/default/propertiestool.xml
medialog/mascutheme/profiles/default/skins.xml
medialog/mascutheme/profiles/default/viewlets.xml
medialog/mascutheme/skins/.DS_Store
medialog/mascutheme/skins/medialog_mascutheme_custom_images/000forlopvII.jpg
medialog/mascutheme/skins/medialog_mascutheme_custom_images/BGmaritime_hvit_logo.png
medialog/mascutheme/skins/medialog_mascutheme_custom_images/Email.png
medialog/mascutheme/skins/medialog_mascutheme_custom_images/Featureclose.png
medialog/mascutheme/skins/medialog_mascutheme_custom_images/RSS.png
medialog/mascutheme/skins/medialog_mascutheme_custom_images/arrow.gif
medialog/mascutheme/skins/medialog_mascutheme_custom_images/arrow_back.gif
