Metadata-Version: 1.0
Name: medialog.mascutheme
Version: 0.1
Summary: Medialog Mascutheme
Home-page: http://github.com/espenmn/medialog.mascutheme
Author: EMN
Author-email: espen@medialog.no
License: GPL
Keywords: Plone Theme Mascutheme
Platform: UNKNOWN
Classifier: Framework :: Plone
Classifier: Programming Language :: Python
